odoo/addons/ir_sequence_standard_default/README.rst
odoo/addons/ir_sequence_standard_default/__init__.py
odoo/addons/ir_sequence_standard_default/__manifest__.py
odoo/addons/ir_sequence_standard_default/i18n/ir_sequence_standard_default.pot
odoo/addons/ir_sequence_standard_default/models/__init__.py
odoo/addons/ir_sequence_standard_default/models/res_config_settings.py
odoo/addons/ir_sequence_standard_default/readme/CONTRIBUTORS.rst
odoo/addons/ir_sequence_standard_default/readme/DESCRIPTION.rst
odoo/addons/ir_sequence_standard_default/static/description/icon.png
odoo/addons/ir_sequence_standard_default/static/description/index.html
odoo/addons/ir_sequence_standard_default/tests/__init__.py
odoo/addons/ir_sequence_standard_default/tests/test_sequence_standard_default.py
odoo/addons/ir_sequence_standard_default/views/res_config_settings_views.xml
odoo/addons/ir_sequence_standard_default/wizard/__init__.py
odoo/addons/ir_sequence_standard_default/wizard/sequence_standard_default.py
odoo/addons/ir_sequence_standard_default/wizard/sequence_standard_default_views.xml
odoo12_addon_ir_sequence_standard_default-12.0.1.0.0.99.dev3.dist-info/METADATA
odoo12_addon_ir_sequence_standard_default-12.0.1.0.0.99.dev3.dist-info/WHEEL
odoo12_addon_ir_sequence_standard_default-12.0.1.0.0.99.dev3.dist-info/top_level.txt
odoo12_addon_ir_sequence_standard_default-12.0.1.0.0.99.dev3.dist-info/RECORD
